setup.py
easycordeyy/main.py
easycordeyy.egg-info/PKG-INFO
easycordeyy.egg-info/SOURCES.txt
easycordeyy.egg-info/dependency_links.txt
easycordeyy.egg-info/top_level.txt